CHANGELOG.rst
LICENSE.txt
MANIFEST.in
README.rst
requirements.txt
setup.cfg
setup.py
versioneer.py
httpsig/__init__.py
httpsig/_version.py
httpsig/requests_auth.py
httpsig/sign.py
httpsig/utils.py
httpsig/verify.py
httpsig/tests/__init__.py
httpsig/tests/rsa_private.pem
httpsig/tests/rsa_public.pem
httpsig/tests/test_signature.py
httpsig/tests/test_utils.py
httpsig/tests/test_verify.py
matthisk_httpsig.egg-info/PKG-INFO
matthisk_httpsig.egg-info/SOURCES.txt
matthisk_httpsig.egg-info/dependency_links.txt
matthisk_httpsig.egg-info/requires.txt
matthisk_httpsig.egg-info/top_level.txt
matthisk_httpsig.egg-info/zip-safe